safpis/__about__.py
safpis/__init__.py
safpis/api.py
safpis/cli.py
safpis/models.py
safpis/safpis.py
safpis-0.2.8.dist-info/METADATA
safpis-0.2.8.dist-info/WHEEL
safpis-0.2.8.dist-info/licenses/AUTHORS.rst
safpis-0.2.8.dist-info/licenses/LICENSE
safpis-0.2.8.dist-info/RECORD
