Metadata-Version: 2.1
Name: safpis
Version: 0.2.8
Summary:     SAFPIS is a Python library to access the South Australia Fuel Pricing     Information Scheme (SAFPIS) REST API.
Project-URL: Documentation, https://safpis.readthedocs.io
Project-URL: Repository, https://github.com/nathanhaigh/safpis.git
Project-URL: Issues, https://github.com/nathanhaigh/safpis/issues
Project-URL: History, https://github.com/nathanhaigh/safpis/blob/main/HISTORY.rst
Author-email: Nathan Watson-Haigh <nathan@watsonhaigh.net>
License: MIT License
License-File: AUTHORS.rst
License-File: LICENSE
Keywords: Fuel,Petrol,South Australia,safpis
Classifier: Development Status :: 3 - Alpha
Classifier: Intended Audience :: Developers
Classifier: Intended Audience :: End Users/Desktop
Classifier: License :: OSI Approved :: MIT License
Classifier: Natural Language :: English
Classifier: Operating System :: OS Independent
Classifier: Programming Language :: Python :: 3
Classifier: Programming Language :: Python :: 3.5
Classifier: Programming Language :: Python :: 3.6
Classifier: Programming Language :: Python :: 3.7
Classifier: Programming Language :: Python :: 3.8
Classifier: Programming Language :: Python :: 3.9
Classifier: Programming Language :: Python :: 3.10
Classifier: Programming Language :: Python :: 3.11
Classifier: Programming Language :: Python :: 3.12
Classifier: Topic :: Home Automation
Requires-Python: >=3.5
Requires-Dist: click>=6.0
Requires-Dist: geopy>=1.13.0
Requires-Dist: money>=1.0
Requires-Dist: python-dateutil>=2.7.0
Requires-Dist: pytz
Requires-Dist: requests-cache>=0.9.1
Requires-Dist: setuptools
